README.md
setup.py
ida_is/__init__.py
ida_is/ida_is.py
ida_is.egg-info/PKG-INFO
ida_is.egg-info/SOURCES.txt
ida_is.egg-info/dependency_links.txt
ida_is.egg-info/top_level.txt