Metadata-Version: 2.1
Name: ida-is
Version: 0.0.6
Summary: TBA
Home-page: https://github.com/sfinktah/ida-is
Author: Christopher Anderson
Author-email: sfinktah@github.spamtrak.org
License: MIT
Platform: UNKNOWN
Classifier: Programming Language :: Python :: 3
Classifier: Programming Language :: Python :: 2
Classifier: License :: OSI Approved :: MIT License
Classifier: Operating System :: OS Independent
Requires-Python: >=2.7
